multilang_probe/__init__.py
multilang_probe/character_detection.py
multilang_probe/cli.py
multilang_probe/corpus_analysis.py
multilang_probe/language_detection.py
multilang_probe/math_detection.py
multilang_probe/visualization.py
multilang_probe-1.1.2.dist-info/METADATA
multilang_probe-1.1.2.dist-info/WHEEL
multilang_probe-1.1.2.dist-info/entry_points.txt
multilang_probe-1.1.2.dist-info/top_level.txt
multilang_probe-1.1.2.dist-info/RECORD
