Metadata-Version: 2.4
Name: multilang-probe
Version: 1.1.2
Summary: A Python package for analyzing multilingual text.
Author-email: Florian Cafiero <florian.cafiero@chartes.psl.eu>
License: MIT
Classifier: Programming Language :: Python :: 3
Requires-Dist: fasttext>=0.8.20
Requires-Dist: pybind11
Requires-Dist: matplotlib
Requires-Dist: regex
